cxloperatorsdk/__init__.py
cxloperatorsdk/operator.py
cxloperatorsdk/operator_exception.py
cxloperatorsdk/run_status.py
cxloperatorsdk-1.0.6.dist-info/METADATA
cxloperatorsdk-1.0.6.dist-info/WHEEL
cxloperatorsdk-1.0.6.dist-info/top_level.txt
cxloperatorsdk-1.0.6.dist-info/RECORD
